textbase/__init__.py
textbase/textbase_cli.py
textbase_cli-0.1.1.dist-info/METADATA
textbase_cli-0.1.1.dist-info/WHEEL
textbase_cli-0.1.1.dist-info/entry_points.txt
textbase_cli-0.1.1.dist-info/RECORD
