Metadata-Version: 2.1
Name: textbase-cli
Version: 0.1.1
Summary: A python library to help you create chatbots easily with some more configurations
Author: kaus-cofactory
Author-email: kaustubhshukla@cofactory.ai
Requires-Python: >=3.8.1,<4.0.0
Classifier: Programming Language :: Python :: 3
Classifier: Programming Language :: Python :: 3.9
Classifier: Programming Language :: Python :: 3.10
Classifier: Programming Language :: Python :: 3.11
Requires-Dist: fastapi
Requires-Dist: openai (>=0.27.8,<0.28.0)
Requires-Dist: pydantic (>=2.1.1,<3.0.0)
Requires-Dist: python-dotenv (>=1.0.0,<2.0.0)
Requires-Dist: requests (>=2.31.0,<3.0.0)
Requires-Dist: tabulate (>=0.9.0,<0.10.0)
Requires-Dist: twilio (>=8.5.0,<9.0.0)
Requires-Dist: uvicorn
